trench/__init__.py
trench-0.0.1.dist-info/LICENSE.txt
trench-0.0.1.dist-info/METADATA
trench-0.0.1.dist-info/WHEEL
trench-0.0.1.dist-info/top_level.txt
trench-0.0.1.dist-info/RECORD
