Metadata-Version: 2.1
Name: trench
Version: 0.0.1
Summary: Deep learning library
Home-page: https://github.com/slothai/pytrench
Author: Kirill Pavlov
Author-email: k@p99.io
License: UNKNOWN
Platform: UNKNOWN
Classifier: Programming Language :: Python :: 3
Classifier: License :: OSI Approved :: MIT License
Classifier: Operating System :: OS Independent
Requires-Python: >=3.5
